docxify/__init__.py
docxify/scratch_pad.py
docxify-0.1.3.dist-info/LICENSE
docxify-0.1.3.dist-info/METADATA
docxify-0.1.3.dist-info/WHEEL
docxify-0.1.3.dist-info/entry_points.txt
docxify-0.1.3.dist-info/top_level.txt
docxify-0.1.3.dist-info/RECORD
